webthing_client/__init__.py
webthing_client/client.py
webthing_client/input/action/event_input.py
webthing_client/input/action/event_type_input.py
webthing_client/input/action/from_to_user_input.py
webthing_client/input/action/iri_user_input.py
webthing_client/input/action/resolution_input.py
webthing_client/input/from_to_input.py
webthing_client/input/iri_input.py
webthing_client/input/property/observations_input.py
webthing_client/input/property/properties_input.py
webthing_client/input/replay/replay_input.py
webthing_client/model/action/action.py
webthing_client/model/action/base.py
webthing_client/model/action/operation/operation.py
webthing_client/model/action/request.py
webthing_client/model/action/resolution.py
webthing_client/model/event/event.py
webthing_client/model/event/event_type.py
webthing_client/model/event/feedback.py
webthing_client/model/event/feedback_schema.py
webthing_client/model/event/observation.py
webthing_client/model/event/stimulus.py
webthing_client/model/ontology.py
webthing_client/model/property/observable_property.py
webthing_client/model/replay/replay.py
webthing_client/model/system/sensor.py
webthing_client/model/system/system.py
webthing_client/model/user/user.py
webthing_client/model/webthing_observation.py
webthing_client/standard_api/__init__.py
webthing_client/standard_api/api_handler.py
webthing_client/standard_api/api_marshalling.py
webthing_client/stomp.py
webthing_client/utils.py
webthing_client-0.2.14.dist-info/LICENSE
webthing_client-0.2.14.dist-info/METADATA
webthing_client-0.2.14.dist-info/WHEEL
webthing_client-0.2.14.dist-info/RECORD
